individual/__init__.py
individual/admin.py
individual/apps.py
individual/custom_filters.py
individual/data_masking.py
individual/documents.py
individual/gql_mutations.py
individual/gql_queries.py
individual/models.py
individual/schema.py
individual/services.py
individual/urls.py
individual/utils.py
individual/validation.py
individual/views.py
individual/management/__init__.py
individual/management/commands/__init__.py
individual/management/commands/fake_individuals.py
individual/migrations/0001_initial.py
individual/migrations/0002_add_individual_rigts_for_admin.py
individual/migrations/0003_group_groupindividual_historicalgroup_historicalgroupindividual.py
individual/migrations/0004_add_group_rights_to_admin.py
individual/migrations/0005_auto_20230621_1323.py
individual/migrations/0006_auto_20230621_1544.py
individual/migrations/0007_auto_20230630_0950.py
individual/migrations/0008_auto_20240105_1527.py
individual/migrations/0009_auto_20240109_0953.py
individual/migrations/0010_auto_20240109_1140.py
individual/migrations/0011_auto_20240131_1015.py
individual/migrations/0012_auto_20240516_1029.py
individual/migrations/0013_add_group_code.py
individual/migrations/0014_auto_20240526_2009.py
individual/migrations/0015_auto_20240527_2220.py
individual/migrations/0016_remove_recipient_from_role.py
individual/migrations/0017_remove_historicalindividualdatasourceupload_individual_and_more.py
individual/migrations/0018_alter_groupindividual_role_and_more.py
individual/migrations/__init__.py
individual/signals/__init__.py
individual/signals/on_validation_import_valid_items.py
individual/tests/__init__.py
individual/tests/data.py
individual/tests/graphql_mutation_group_test.py
individual/tests/graphql_mutation_individual_test.py
individual/tests/graphql_query_test.py
individual/tests/group_individual_service_test.py
individual/tests/group_service_test.py
individual/tests/individual_import_service_test.py
individual/tests/individual_service_test.py
openimis_be_individual-1.3.1.dist-info/licenses/LICENSE.md
openimis_be_individual-1.3.1.dist-info/METADATA
openimis_be_individual-1.3.1.dist-info/WHEEL
openimis_be_individual-1.3.1.dist-info/top_level.txt
openimis_be_individual-1.3.1.dist-info/RECORD
